myutils/__init__.py
myutils/ai_embed_manager_utils.py
myutils/ai_manager_utils.py
myutils/database_manager_utils.py
myutils/date_utils.py
myutils/file_utils.py
myutils/sentry_manager_utils.py
myutils/string_utils.py
myutils/validation_utils.py
python_myutils-1.0.2.dist-info/licenses/LICENSE
python_myutils-1.0.2.dist-info/METADATA
python_myutils-1.0.2.dist-info/WHEEL
python_myutils-1.0.2.dist-info/top_level.txt
python_myutils-1.0.2.dist-info/RECORD
