Metadata-Version: 2.4
Name: python-myutils
Version: 1.0.2
Summary: A comprehensive Python utility library with AI integration, database operations, and common utilities
Author-email: quocln-tech <quocln@me.com>
License-Expression: MIT
Project-URL: Homepage, https://github.com/quocln-tech/python-myutils
Project-URL: Repository, https://github.com/quocln-tech/python-myutils
Project-URL: Bug Tracker, https://github.com/quocln-tech/python-myutils/issues
Project-URL: Documentation, https://github.com/quocln-tech/python-myutils#readme
Project-URL: Source Code, https://github.com/quocln-tech/python-myutils
Keywords: utilities,ai,database,validation,file-utils,string-utils,openai,supabase,sentry
Classifier: Development Status :: 5 - Production/Stable
Classifier: Intended Audience :: Developers
Classifier: Operating System :: OS Independent
Classifier: Programming Language :: Python :: 3
Classifier: Programming Language :: Python :: 3.10
Classifier: Programming Language :: Python :: 3.11
Classifier: Programming Language :: Python :: 3.12
Classifier: Programming Language :: Python :: 3.13
Classifier: Topic :: Software Development :: Libraries :: Python Modules
Classifier: Topic :: Utilities
Requires-Python: >=3.10
License-File: LICENSE
Requires-Dist: requests>=2.32.4
Requires-Dist: supabase>=2.16.0
Requires-Dist: sentry-sdk>=2.32.0
Requires-Dist: python-dotenv>=1.0.0
Provides-Extra: dev
Requires-Dist: pytest>=7.0.0; extra == "dev"
Requires-Dist: pytest-cov>=4.0.0; extra == "dev"
Requires-Dist: pytest-mock>=3.10.0; extra == "dev"
Provides-Extra: all
Requires-Dist: pytest>=7.0.0; extra == "all"
Requires-Dist: pytest-cov>=4.0.0; extra == "all"
Requires-Dist: pytest-mock>=3.10.0; extra == "all"
Dynamic: license-file
